mkstuff/__init__.py
mkstuff/athena.py
mkstuff/info.py
mkstuff/mkplot.py
mkstuff/mkstuff.py
mkstuff/nicaea.py
mkstuff/populationWL.py
mkstuff/example/__init__.py
mkstuff/example/hello.py
mkstuff/example/math.py
mkstuff/tests/__init__.py
mkstuff/tests/test_example.py
mkstuff/tests/test_mkstuff.py
mkstuff-1.2.2.data/scripts/ascii2fits.py
mkstuff-1.2.2.data/scripts/fits2ascii.py
mkstuff-1.2.2.dist-info/DESCRIPTION.rst
mkstuff-1.2.2.dist-info/METADATA
mkstuff-1.2.2.dist-info/RECORD
mkstuff-1.2.2.dist-info/WHEEL
mkstuff-1.2.2.dist-info/metadata.json
mkstuff-1.2.2.dist-info/top_level.txt
