Metadata-Version: 2.0
Name: mkstuff
Version: 1.2.2
Summary: builtins 
Requires-Dist: astropy
Requires-Dist: numpy
Requires-Dist: scipy
